MANIFEST.in
README.md
setup.py
ftoolz/__init__.py
ftoolz/dicttoolz.py
ftoolz/itertoolz.py
ftoolz/predicates.py
ftoolz/py.typed
ftoolz/typing.py
ftoolz.egg-info/PKG-INFO
ftoolz.egg-info/SOURCES.txt
ftoolz.egg-info/dependency_links.txt
ftoolz.egg-info/not-zip-safe
ftoolz.egg-info/requires.txt
ftoolz.egg-info/top_level.txt
ftoolz/adt/__init__.py
ftoolz/adt/mutiter.py
ftoolz/functoolz/__init__.py
ftoolz/functoolz/iter.py
ftoolz/functoolz/opt.py
ftoolz/functoolz/seq.py
ftoolz/functoolz/traverse/__init__.py
ftoolz/functoolz/traverse/opt.py
ftoolz/unsafe/__init__.py
ftoolz/unsafe/reflection.py
tests/test_unsafe/__init__.py
tests/test_unsafe/classes.py
tests/test_unsafe/test_reflection.py