Metadata-Version: 2.1
Name: ftoolz
Version: 0.4.0
Summary: Collection of higher-order and utility functions
Home-page: https://github.com/blindspot-ai/ftoolz
Maintainer: Martin Matyasek
Maintainer-email: martin.matyasek@blindspot.ai
License: MIT
Keywords: functional utility cytoolz itertools functools
Platform: UNKNOWN
Classifier: Development Status :: 4 - Beta
Classifier: Environment :: Console
Classifier: Intended Audience :: Developers
Classifier: Natural Language :: English
Classifier: Operating System :: Unix
Classifier: Programming Language :: Python
Classifier: Programming Language :: Python :: 3
Classifier: Programming Language :: Python :: 3.6
Classifier: Programming Language :: Python :: 3.7
Classifier: Programming Language :: Python :: 3.8
Requires-Python: >=3.6
Provides-Extra: dev
Provides-Extra: test
